bmsdna/mailing/__init__.py
bmsdna/mailing/basicazure.py
bmsdna/mailing/config.py
bmsdna/mailing/execute.py
bmsdna/mailing/generation_context.py
bmsdna/mailing/message.py
bmsdna/mailing/message_io.py
bmsdna/mailing/persistance.py
bmsdna/mailing/registry.py
bmsdna/mailing/sendgrid.py
bmsdna/mailing/sending.py
bmsdna/mailing/storage.py
bmsdna/mailing/attachments/__init__.py
bmsdna/mailing/attachments/powerbi_attachment.py
bmsdna/mailing/attachments/reference_attachment.py
bmsdna/mailing/attachments/static_attachment.py
bmsdna/mailing/scheduling/__init__.py
bmsdna/mailing/scheduling/schedule.py
bmsdna_mailing-0.8.11.dist-info/METADATA
bmsdna_mailing-0.8.11.dist-info/WHEEL
bmsdna_mailing-0.8.11.dist-info/RECORD
